pdf_statement_reader/__init__.py
pdf_statement_reader/decrypt.py
pdf_statement_reader/parse.py
pdf_statement_reader/validate.py
pdf_statement_reader/config/psr_config.schema.json
pdf_statement_reader/config/za/absa/cheque-sample.json
pdf_statement_reader/config/za/absa/cheque.json
pdf_statement_reader-0.3.4.dist-info/METADATA
pdf_statement_reader-0.3.4.dist-info/WHEEL
pdf_statement_reader-0.3.4.dist-info/entry_points.txt
pdf_statement_reader-0.3.4.dist-info/licenses/LICENSE
pdf_statement_reader-0.3.4.dist-info/RECORD
