Metadata-Version: 2.4
Name: pdf-statement-reader
Version: 0.3.4
Summary: PDF Statement Reader
Project-URL: issues, https://github.com/marlanperumal/pdf_statement_reader/issues
Project-URL: source, https://github.com/marlanperumal/pdf_statement_reader
Project-URL: homepage, https://github.com/marlanperumal/pdf_statement_reader
Author-email: Marlan Perumal <marlan.perumal@gmail.com>
License: MIT License
License-File: LICENSE
Keywords: bank statement,digitise,pdf,reader,statement
Classifier: Development Status :: 3 - Alpha
Classifier: Intended Audience :: Developers
Classifier: License :: OSI Approved :: MIT License
Classifier: Operating System :: OS Independent
Classifier: Programming Language :: Python :: 3.13
Classifier: Topic :: Office/Business :: Financial
Requires-Python: >=3.13
Requires-Dist: click>=8.1.8
Requires-Dist: pikepdf>=9.5.1
Requires-Dist: tabula-py[jpype]>=2.10.0
